tidi/__init__.py
tidi/decorator.py
tidi/parameters.py
tidi/py.typed
tidi/registry.py
tidi/resolver.py
tidi-0.3.0.dist-info/LICENSE
tidi-0.3.0.dist-info/METADATA
tidi-0.3.0.dist-info/WHEEL
tidi-0.3.0.dist-info/RECORD
